{"id":213418,"name":"万古仙穹","name_cn":"万古仙穹","type":"动画","image":"75/50/213418_2IPS2.jpg","link":"https://bgm.tv/subject/213418","eps":12,"collection":{"on_hold":7,"dropped":10,"wish":17,"collect":66,"doing":4},"date":"2017-05-18","summary":"一枚围棋棋子，将本是生活在21世纪的商界精英古海带到了一个陌生的世界。在这个世界古海成为了富可敌国的商人，一次国家大战中，他凭借自己过人的谋略和财力成功帮助陈国从灭国的危机中逃脱。因为智谋过人，于是古海被上仙看中，受命去完成一个神秘任务，一场沉重的阴谋和杀戮即将展开，在大义与友情面前，古海的选择是什么，他又能否完成任务，得到上仙新的点化呢？","rating":{"rank":0,"total":41,"count":{"1":2,"2":0,"3":0,"4":0,"5":5,"6":14,"7":13,"8":4,"9":1,"10":2},"score":6.4},"updated_at":"2023-06-24T18:37:37+08:00"}